stevools/__init__.py
stevools/collection_utils.py
stevools/date_utils.py
stevools/format_utils.py
stevools/os_utils.py
stevools/pool_utils.py
stevools/re_utils.py
stevools/string_utils.py
stevools/util_classes.py
stevools/io_utils/__init__.py
stevools/io_utils/base_io.py
stevools/io_utils/pandas_io.py
stevools/multiprocess/__init__.py
stevools/multiprocess/parallel_executor.py
stevools/multiprocess/task.py
stevools/multiprocess/task_spliter.py
stevools/scripts/__init__.py
stevools/scripts/ls_py.py
stevools-0.1.2.dist-info/LICENSE
stevools-0.1.2.dist-info/METADATA
stevools-0.1.2.dist-info/WHEEL
stevools-0.1.2.dist-info/entry_points.txt
stevools-0.1.2.dist-info/top_level.txt
stevools-0.1.2.dist-info/RECORD
