Metadata-Version: 2.1
Name: stevools
Version: 0.1.2
Author: steveflyer
Author-email: 
License-File: LICENSE
Requires-Dist: uuid
Requires-Dist: pandas
